openstf/__init__.py
openstf/__main__.py
openstf/enums.py
openstf/exceptions.py
openstf/data/dutch_holidays_2020-2022.csv
openstf/data/dutch_holidays_2020-2022.csv.license
openstf/data/pv_single_coefs.csv
openstf/data/pv_single_coefs.csv.license
openstf/data_classes/__init__.py
openstf/data_classes/model_specifications.py
openstf/feature_engineering/__init__.py
openstf/feature_engineering/apply_features.py
openstf/feature_engineering/feature_applicator.py
openstf/feature_engineering/general.py
openstf/feature_engineering/historic_features.py
openstf/feature_engineering/holiday_features.py
openstf/feature_engineering/lag_features.py
openstf/feature_engineering/weather_features.py
openstf/metrics/__init__.py
openstf/metrics/figure.py
openstf/metrics/metrics.py
openstf/metrics/reporter.py
openstf/model/__init__.py
openstf/model/basecase.py
openstf/model/confidence_interval_applicator.py
openstf/model/fallback.py
openstf/model/model_creator.py
openstf/model/objective.py
openstf/model/objective_creator.py
openstf/model/serializer.py
openstf/model/standard_deviation_generator.py
openstf/model/metamodels/__init__.py
openstf/model/metamodels/missing_values_handler.py
openstf/model/regressors/__init__.py
openstf/model/regressors/lgbm.py
openstf/model/regressors/linear.py
openstf/model/regressors/proloaf.py
openstf/model/regressors/regressor.py
openstf/model/regressors/regressor_interface.py
openstf/model/regressors/xgb.py
openstf/model/regressors/xgb_quantile.py
openstf/model_selection/__init__.py
openstf/model_selection/model_selection.py
openstf/monitoring/__init__.py
openstf/monitoring/performance_meter.py
openstf/monitoring/teams.py
openstf/pipeline/__init__.py
openstf/pipeline/create_basecase_forecast.py
openstf/pipeline/create_component_forecast.py
openstf/pipeline/create_forecast.py
openstf/pipeline/optimize_hyperparameters.py
openstf/pipeline/train_create_forecast_backtest.py
openstf/pipeline/train_model.py
openstf/pipeline/utils.py
openstf/postprocessing/__init__.py
openstf-2.6.4.dist-info/LICENSE
openstf-2.6.4.dist-info/METADATA
openstf-2.6.4.dist-info/WHEEL
openstf-2.6.4.dist-info/top_level.txt
openstf-2.6.4.dist-info/RECORD
