Metadata-Version: 2.1
Name: openstf
Version: 2.6.4
Summary: Open short term forcasting
Home-page: https://github.com/alliander-opensource/openstf
Author: Alliander N.V
Author-email: korte.termijn.prognoses@alliander.com
License: MPL-2.0
Keywords: energy,forecasting,machinelearning
Platform: UNKNOWN
Classifier: Development Status :: 5 - Production/Stable
Classifier: Intended Audience :: Developers
Classifier: License :: OSI Approved :: Mozilla Public License 2.0 (MPL 2.0)
Classifier: Programming Language :: Python :: 3.7
Classifier: Programming Language :: Python :: 3.8
Classifier: Programming Language :: Python :: 3.9
Requires-Python: >=3.7.0
License-File: LICENSE
Requires-Dist: Cython (~=0.29.21)
Requires-Dist: cufflinks (~=0.17.3)
Requires-Dist: dill (~=0.3.3)
Requires-Dist: holidays (~=0.10.5.2)
Requires-Dist: lightgbm (~=3.1.1)
Requires-Dist: numpy (~=1.20.0)
Requires-Dist: optuna (~=2.5.0)
Requires-Dist: openstf-dbc (~=2.2.0)
Requires-Dist: pandas (~=1.2.1)
Requires-Dist: plotly (~=4.14.3)
Requires-Dist: pre-commit (~=2.13.0)
Requires-Dist: pymsteams (~=0.1.14)
Requires-Dist: pytz (~=2021.1)
Requires-Dist: requests (~=2.25.1)
Requires-Dist: scikit-learn (~=0.24.1)
Requires-Dist: scipy (~=1.6.0)
Requires-Dist: setuptools (~=45.2.0)
Requires-Dist: sklearn (~=0.0)
Requires-Dist: wheel (~=0.36.2)
Requires-Dist: xgboost (~=1.3.3)
Requires-Dist: structlog (<21,>=20)
Requires-Dist: pydantic (~=1.8.2)
Requires-Dist: mlflow (~=1.21.0)
Requires-Dist: matplotlib (~=3.3.4)
Provides-Extra: proloaf
Requires-Dist: proloaf (==0.2.0) ; extra == 'proloaf'
Requires-Dist: torch (==1.10.0) ; extra == 'proloaf'
Requires-Dist: pytorch-lightning (==1.5.1) ; extra == 'proloaf'
